irisai/__init__.py
irisai/client.py
IrisAI-1.0.dist-info/METADATA
IrisAI-1.0.dist-info/WHEEL
IrisAI-1.0.dist-info/top_level.txt
IrisAI-1.0.dist-info/RECORD
