Metadata-Version: 2.1
Name: IrisAI
Version: 1.0
Summary: IrisAI API Connector
Author: Tes
Author-email: dev@tesnpe.ru
Keywords: IrisAI
Classifier: Programming Language :: Python :: 3.12
Classifier: License :: OSI Approved :: MIT License
Classifier: Operating System :: OS Independent
Requires-Python: >=3.12
Requires-Dist: requests
